<?xml version="1.0" encoding="utf-8"?>
<Defs>

	<PortraitsOfTheRim.PortraitElementDef>
		<defName>PR_InnerClothingShoulder_VEAccessories-l-Backpack</defName>
		<portraitLayer>PR_InnerClothingShoulder</portraitLayer>
		<graphicData>
			<texPath>InnerClothingShoulder/VEAccessories-l-Backpack</texPath>
		</graphicData>
		<requirements>
			<bodyType>Large</bodyType>
			<apparels>
				<li>VAEA_Apparel_Backpack</li>
			</apparels>
		</requirements>
	</PortraitsOfTheRim.PortraitElementDef>

	<PortraitsOfTheRim.PortraitElementDef>
		<defName>PR_InnerClothingShoulder_VEAccessories-l-battlebanner</defName>
		<portraitLayer>PR_InnerClothingShoulder</portraitLayer>
		<graphicData>
			<texPath>InnerClothingShoulder/VEAccessories-l-battlebanner</texPath>
		</graphicData>
		<requirements>
			<bodyType>Large</bodyType>
			<apparels>
				<li>VAEA_Apparel_BattleBanner</li>
			</apparels>
		</requirements>
	</PortraitsOfTheRim.PortraitElementDef>

	<PortraitsOfTheRim.PortraitElementDef>
		<defName>PR_InnerClothingShoulder_VEAccessories-l-Miniturretpack</defName>
		<portraitLayer>PR_InnerClothingShoulder</portraitLayer>
		<graphicData>
			<texPath>InnerClothingShoulder/VEAccessories-l-Miniturretpack</texPath>
		</graphicData>
		<requirements>
			<bodyType>Large</bodyType>
			<apparels>
				<li>VAEA_Apparel_MiniTurretPack</li>
			</apparels>
		</requirements>
	</PortraitsOfTheRim.PortraitElementDef>

	<PortraitsOfTheRim.PortraitElementDef>
		<defName>PR_InnerClothingShoulder_VEAccessories-l-Quiver</defName>
		<portraitLayer>PR_InnerClothingShoulder</portraitLayer>
		<graphicData>
			<texPath>InnerClothingShoulder/VEAccessories-l-Quiver</texPath>
		</graphicData>
		<requirements>
			<bodyType>Large</bodyType>
			<apparels>
				<li>VAEA_Apparel_Quiver</li>
			</apparels>
		</requirements>
	</PortraitsOfTheRim.PortraitElementDef>

	<PortraitsOfTheRim.PortraitElementDef>
		<defName>PR_InnerClothingShoulder_VEAccessories-m-Backpack</defName>
		<portraitLayer>PR_InnerClothingShoulder</portraitLayer>
		<graphicData>
			<texPath>InnerClothingShoulder/VEAccessories-m-Backpack</texPath>
		</graphicData>
		<requirements>
			<bodyType>Medium</bodyType>
			<apparels>
				<li>VAEA_Apparel_Backpack</li>
			</apparels>
		</requirements>
	</PortraitsOfTheRim.PortraitElementDef>

	<PortraitsOfTheRim.PortraitElementDef>
		<defName>PR_InnerClothingShoulder_VEAccessories-m-battlebanner</defName>
		<portraitLayer>PR_InnerClothingShoulder</portraitLayer>
		<graphicData>
			<texPath>InnerClothingShoulder/VEAccessories-m-battlebanner</texPath>
		</graphicData>
		<requirements>
			<bodyType>Medium</bodyType>
			<apparels>
				<li>VAEA_Apparel_BattleBanner</li>
			</apparels>
		</requirements>
	</PortraitsOfTheRim.PortraitElementDef>

	<PortraitsOfTheRim.PortraitElementDef>
		<defName>PR_InnerClothingShoulder_VEAccessories-m-Miniturretpack</defName>
		<portraitLayer>PR_InnerClothingShoulder</portraitLayer>
		<graphicData>
			<texPath>InnerClothingShoulder/VEAccessories-m-Miniturretpack</texPath>
		</graphicData>
		<requirements>
			<bodyType>Medium</bodyType>
			<apparels>
				<li>VAEA_Apparel_MiniTurretPack</li>
			</apparels>
		</requirements>
	</PortraitsOfTheRim.PortraitElementDef>

	<PortraitsOfTheRim.PortraitElementDef>
		<defName>PR_InnerClothingShoulder_VEAccessories-m-Quiver</defName>
		<portraitLayer>PR_InnerClothingShoulder</portraitLayer>
		<graphicData>
			<texPath>InnerClothingShoulder/VEAccessories-m-Quiver</texPath>
		</graphicData>
		<requirements>
			<bodyType>Medium</bodyType>
			<apparels>
				<li>VAEA_Apparel_Quiver</li>
			</apparels>
		</requirements>
	</PortraitsOfTheRim.PortraitElementDef>

	<PortraitsOfTheRim.PortraitElementDef>
		<defName>PR_InnerClothingShoulder_VEAccessories-s-Backpack</defName>
		<portraitLayer>PR_InnerClothingShoulder</portraitLayer>
		<graphicData>
			<texPath>InnerClothingShoulder/VEAccessories-s-Backpack</texPath>
		</graphicData>
		<requirements>
			<bodyType>Small</bodyType>
			<apparels>
				<li>VAEA_Apparel_Backpack</li>
			</apparels>
		</requirements>
	</PortraitsOfTheRim.PortraitElementDef>

	<PortraitsOfTheRim.PortraitElementDef>
		<defName>PR_InnerClothingShoulder_VEAccessories-s-battlebanner</defName>
		<portraitLayer>PR_InnerClothingShoulder</portraitLayer>
		<graphicData>
			<texPath>InnerClothingShoulder/VEAccessories-s-battlebanner</texPath>
		</graphicData>
		<requirements>
			<bodyType>Small</bodyType>
			<apparels>
				<li>VAEA_Apparel_BattleBanner</li>
			</apparels>
		</requirements>
	</PortraitsOfTheRim.PortraitElementDef>

	<PortraitsOfTheRim.PortraitElementDef>
		<defName>PR_InnerClothingShoulder_VEAccessories-s-Miniturretpack</defName>
		<portraitLayer>PR_InnerClothingShoulder</portraitLayer>
		<graphicData>
			<texPath>InnerClothingShoulder/VEAccessories-s-Miniturretpack</texPath>
		</graphicData>
		<requirements>
			<bodyType>Small</bodyType>
			<apparels>
				<li>VAEA_Apparel_MiniTurretPack</li>
			</apparels>
		</requirements>
	</PortraitsOfTheRim.PortraitElementDef>

	<PortraitsOfTheRim.PortraitElementDef>
		<defName>PR_InnerClothingShoulder_VEAccessories-s-Quiver</defName>
		<portraitLayer>PR_InnerClothingShoulder</portraitLayer>
		<graphicData>
			<texPath>InnerClothingShoulder/VEAccessories-s-Quiver</texPath>
		</graphicData>
		<requirements>
			<bodyType>Small</bodyType>
			<apparels>
				<li>VAEA_Apparel_Quiver</li>
			</apparels>
		</requirements>
	</PortraitsOfTheRim.PortraitElementDef>

	<PortraitsOfTheRim.PortraitElementDef>
		<defName>PR_InnerClothingShoulder_VEAccessories-xl-Backpack</defName>
		<portraitLayer>PR_InnerClothingShoulder</portraitLayer>
		<graphicData>
			<texPath>InnerClothingShoulder/VEAccessories-xl-Backpack</texPath>
		</graphicData>
		<requirements>
			<bodyType>ExtraLarge</bodyType>
			<apparels>
				<li>VAEA_Apparel_Backpack</li>
			</apparels>
		</requirements>
	</PortraitsOfTheRim.PortraitElementDef>

	<PortraitsOfTheRim.PortraitElementDef>
		<defName>PR_InnerClothingShoulder_VEAccessories-xl-battlebanner</defName>
		<portraitLayer>PR_InnerClothingShoulder</portraitLayer>
		<graphicData>
			<texPath>InnerClothingShoulder/VEAccessories-xl-battlebanner</texPath>
		</graphicData>
		<requirements>
			<bodyType>ExtraLarge</bodyType>
			<apparels>
				<li>VAEA_Apparel_BattleBanner</li>
			</apparels>
		</requirements>
	</PortraitsOfTheRim.PortraitElementDef>

	<PortraitsOfTheRim.PortraitElementDef>
		<defName>PR_InnerClothingShoulder_VEAccessories-xl-Miniturretpack</defName>
		<portraitLayer>PR_InnerClothingShoulder</portraitLayer>
		<graphicData>
			<texPath>InnerClothingShoulder/VEAccessories-xl-Miniturretpack</texPath>
		</graphicData>
		<requirements>
			<bodyType>ExtraLarge</bodyType>
			<apparels>
				<li>VAEA_Apparel_MiniTurretPack</li>
			</apparels>
		</requirements>
	</PortraitsOfTheRim.PortraitElementDef>

	<PortraitsOfTheRim.PortraitElementDef>
		<defName>PR_InnerClothingShoulder_VEAccessories-xl-Quiver</defName>
		<portraitLayer>PR_InnerClothingShoulder</portraitLayer>
		<graphicData>
			<texPath>InnerClothingShoulder/VEAccessories-xl-Quiver</texPath>
		</graphicData>
		<requirements>
			<bodyType>ExtraLarge</bodyType>
			<apparels>
				<li>VAEA_Apparel_Quiver</li>
			</apparels>
		</requirements>
	</PortraitsOfTheRim.PortraitElementDef>
</Defs>